Metadata-Version: 2.1
Name: easypype
Version: 1.2.0
Summary: Easy way of creating pipelines
Home-page: https://github.com/looplex/easypype/tree/main
Author: Gabriel Felix de Souza Lopes <gafelix435@gmail.com>, Alejandro Tarafa Guzmán <alejandro.guzman@looplex.com.br>
License: unlicense
Download-URL: https://github.com/looplex/easypype/archive/refs/tags/v1.2.0.tar.gz
Keywords: Pipeline,ETL,transform,load,pipe
Platform: UNKNOWN
Classifier: Development Status :: 4 - Beta
Classifier: Intended Audience :: Developers
Classifier: Topic :: Software Development :: Libraries :: Python Modules
Classifier: License :: OSI Approved :: MIT License
Classifier: Programming Language :: Python :: 3.6
Classifier: Programming Language :: Python :: 3.7
Classifier: Programming Language :: Python :: 3.8
Classifier: Programming Language :: Python :: 3.9
Classifier: Programming Language :: Python :: 3.10
Requires-Python: >=3.5
